pytest_rt.py
pytest_rt-1.3.2.dist-info/LICENSE
pytest_rt-1.3.2.dist-info/METADATA
pytest_rt-1.3.2.dist-info/WHEEL
pytest_rt-1.3.2.dist-info/entry_points.txt
pytest_rt-1.3.2.dist-info/top_level.txt
pytest_rt-1.3.2.dist-info/RECORD
