Metadata-Version: 2.1
Name: pytest-rt
Version: 1.3.2
Summary: pytest data collector plugin for Testgr
Home-page: https://github.com/and-sm/pytest-rt
Author: Andrey Smirnov
Author-email: and.inbx@gmail.com
License: UNKNOWN
Platform: UNKNOWN
Classifier: Framework :: Pytest
Classifier: Programming Language :: Python :: 3.8
License-File: LICENSE
